setup.cfg
setup.py
anshils/Gaussiandistribution.py
anshils/Generaldistribution.py
anshils/__init__.py
anshils.egg-info/PKG-INFO
anshils.egg-info/SOURCES.txt
anshils.egg-info/dependency_links.txt
anshils.egg-info/top_level.txt
anshils.egg-info/zip-safe