Metadata-Version: 2.1
Name: anshils
Version: 0.1.4
Summary: Gaussian and Binomial distributions
Author-email: i89041056398@gmail.com
